{
  "simple": {
    "A": "water",
    "AB": "father",
    "AD": "father",
    "AG": "crown",
    "AK": "do",
    "AL": "hoe",
    "AM": "wild bull",
    "AN": "god",
    "AP": "window",
    "AR": "grind",
    "AS": "one",
    "ASZ": "one",
    "BAD": "wall",
    "BA": "go out",
    "BAL": "dig",
    "BAN": "bow",
    "BAR": "outside",
    "BI": "he",
    "BU": "animal",
    "BUL": "multiply",
    "BUR": "release",
    "DA": "side",
    "DAG": "good",
    "DAM": "blood",
    "DAR": "split",
    "DI": "judgment",
    "DIB": "seize",
    "DID": "decree",
    "DIL": "single",
    "DIM": "post",
    "DIN": "justice",
    "DISZ": "one",
    "DU": "go",
    "DUB": "tablet",
    "DUG": "good",
    "DUL": "cover",
    "DUMU": "son",
    "DUN": "strong",
    "DUR": "sit",
    "E": "house",
    "EN": "lord",
    "ER": "go down",
    "ESZ": "shrine",
    "GA": "milk",
    "GAL": "great",
    "GAN": "field",
    "GAR": "place",
    "GI": "reed",
    "GID": "long",
    "GIR": "dagger",
    "GISZ": "wood",
    "GU": "neck",
    "GUB": "stand",
    "GUL": "destroy",
    "GUM": "crush",
    "GUR": "turn",
    "HA": "fish",
    "HAL": "divide",
    "HI": "mix",
    "HU": "bird",
    "IB": "angry",
    "ID": "river",
    "IG": "door",
    "IL": "raise",
    "IM": "clay",
    "IN": "eye",
    "IR": "go",
    "ISZ": "break",
    "KA": "mouth",
    "KAK": "weapon",
    "KAM": "bind",
    "KI": "earth",
    "KISZ": "all",
    "KU": "eat",
    "KUR": "land",
    "LA": "hang",
    "LAGAB": "block",
    "LAM": "surround",
    "LI": "oil",
    "LU": "man",
    "LUGAL": "king",
    "MA": "what",
    "ME": "be",
    "MI": "my",
    "MU": "name",
    "MUNUS": "woman",
    "NA": "not",
    "NI": "fear",
    "NU": "not",
    "PA": "branch",
    "RA": "go",
    "RI": "lead",
    "RU": "go",
    "SA": "sinew",
    "SI": "horn",
    "SU": "hand",
    "SZU": "hand",
    "TA": "from",
    "TE": "approach",
    "TI": "approach",
    "TU": "tablet",
    "U": "and",
    "UD": "day",
    "UG": "die",
    "UL": "distant",
    "UM": "mother",
    "UN": "people",
    "UR": "dog",
    "USZ": "foundation",
    "ZA": "you",
    "ZU": "know",
    "BE": "it",
    "HUL": "bad",
    "GIG": "illness",
    "HUL-GIG": "evil disease",
    "DISZ": "one",
    "NA": "not",
    "NU": "not",
    "TE": "approach",
    "INA": "in",
    "ANA": "to",
    "SZA": "that",
    "U": "and",
    "U3": "and",
    "MA": "and",
    "I3": "fat",
    "SZIM": "mix",
    "KI": "place",
    "MIN": "two",
    "SZESZ": "brother",
    "HI": "mix",
    "KA": "mouth",
    "SAG": "head",
    "SZU": "hand",
    "IGI": "eye",
    "AB": "father",
    "BA": "give",
    "SA": "equal",
    "TA": "from",
    "TI": "life",
    "LU2": "man",
    "MUNUS": "woman",
    "DINGIR": "god",
    "NAG": "drink"
  },
  "compounds": {
    "|GISZ.DIN|": "justice",
    "|LUGAL.AN|": "great king",
    "|E.KUR|": "temple"
  },
  "variants": {},
  "annotations": {
    "#": "damaged",
    "!": "corrected",
    "*": "collated",
    "?": "uncertain"
  }
}
